_stories/__init__.py
_stories/actor.py
_stories/argument.py
_stories/exceptions.py
_stories/execute/__init__.py
_stories/execute/coroutine.py
_stories/execute/function.py
_stories/initiate.py
_stories/state.py
_stories/step.py
_stories/story.py
_stories/stubs.py
_stories/union.py
_stories/variable.py
stories/__init__.py
stories/exceptions.py
stories-5.1.0.dist-info/LICENSE
stories-5.1.0.dist-info/WHEEL
stories-5.1.0.dist-info/METADATA
stories-5.1.0.dist-info/RECORD
