Metadata-Version: 2.1
Name: stories
Version: 5.1.0
Summary: Service objects designed with OOP in mind.
Home-page: https://pypi.org/project/stories
License: BSD-2-Clause
Author: Josiah Kaviani
Author-email: proofit404@gmail.com
Classifier: License :: OSI Approved :: BSD License
Classifier: Programming Language :: Python :: 2
Classifier: Programming Language :: Python :: 2.7
Classifier: Programming Language :: Python :: 3
Classifier: Programming Language :: Python :: 3.4
Classifier: Programming Language :: Python :: 3.5
Classifier: Programming Language :: Python :: 3.6
Classifier: Programming Language :: Python :: 3.7
Classifier: Programming Language :: Python :: 3.8
Classifier: Programming Language :: Python :: 3.9
Classifier: Programming Language :: Python :: 3.10
Classifier: Programming Language :: Python :: 3.11
Classifier: Programming Language :: Python :: Implementation :: CPython
Classifier: Programming Language :: Python :: Implementation :: PyPy
Project-URL: Changelog, https://proofit404.github.io/stories/changelog
Project-URL: Documentation, https://proofit404.github.io/stories
Project-URL: Issues, https://github.com/proofit404/stories/issues
Project-URL: Repository, https://github.com/proofit404/stories
Project-URL: Twitter, https://twitter.com/proofit404
